api_assistant/__init__.py
api_assistant/main.py
common/__init__.py
common/interface.py
common/request.py
common/utils.py
openai/__init__.py
openai/main.py
api_assistant-0.3.0.dist-info/METADATA
api_assistant-0.3.0.dist-info/WHEEL
api_assistant-0.3.0.dist-info/entry_points.txt
api_assistant-0.3.0.dist-info/top_level.txt
api_assistant-0.3.0.dist-info/RECORD
