Metadata-Version: 2.1
Name: api-assistant
Version: 0.3.0
Summary: An OpenAI assistant that can be used on top of a OpenAI functions IDL.
License: MIT license
Requires-Dist: annotated-types ==0.6.0
Requires-Dist: anyio ==3.7.1
Requires-Dist: certifi ==2023.7.22
Requires-Dist: charset-normalizer ==3.3.2
Requires-Dist: click ==8.1.7
Requires-Dist: distro ==1.8.0
Requires-Dist: exceptiongroup ==1.1.3
Requires-Dist: h11 ==0.14.0
Requires-Dist: httpcore ==1.0.2
Requires-Dist: httpx ==0.25.1
Requires-Dist: idna ==3.4
Requires-Dist: openai ==1.2.4
Requires-Dist: pydantic ==2.5.0
Requires-Dist: pydantic-core ==2.14.1
Requires-Dist: requests ==2.31.0
Requires-Dist: result ==0.14.0
Requires-Dist: setuptools ==68.2.2
Requires-Dist: sniffio ==1.3.0
Requires-Dist: tqdm ==4.66.1
Requires-Dist: typing-extensions ==4.8.0
Requires-Dist: urllib3 ==2.1.0
